{
  "name": "Bebauungsplan Nr. 187, Dresden-Cossebaude Nr. 4, Wohngebiet Weinbergstraßehier:\t1. Entfallen des frühzeitigen Beteiligungsverfahrens \t2. Billigung des Entwurfes zum Bebauungsplan\t3. Billigung der Begründung zum Bebauungsplan-Entwurf\t4. Durchführung des Beteiligungsverfahrens zum Bebauungsplan-Entwurf",
  "shortName": "V0992/11",
  "reference": "V0992/11",
  "paperType": "Vorlage B-/VB-Pläne/FNP-Änderungen",
  "type": "https://oparl.org/schema/1.0/Paper",
  "publishedDate": "2011-03-17",
  "auxiliaryFile": [
    "64219",
    "58599",
    "58160",
    "58161",
    "58163",
    "58165"
  ],
  "mainFile": "59051",
  "consultation": [

  ],
  "id": "3811"
}