{
  "name": "Bauplanungen in hochwassergefährdeten Gebieten überprüfen - Hochwasservorsorge ernst nehmen",
  "shortName": "A0755/13",
  "reference": "A0755/13",
  "paperType": "Antrag SPD",
  "type": "https://oparl.org/schema/1.0/Paper",
  "publishedDate": "2013-06-28",
  "auxiliaryFile": [
    "137276",
    "159556",
    "158918",
    "157042",
    "158850"
  ],
  "consultation": [
    {
      "type": "https://oparl.org/schema/1.0/Consultation",
      "meeting": "2762"
    },
    {
      "type": "https://oparl.org/schema/1.0/Consultation",
      "meeting": "2693"
    },
    {
      "type": "https://oparl.org/schema/1.0/Consultation",
      "meeting": "2683"
    },
    {
      "type": "https://oparl.org/schema/1.0/Consultation",
      "meeting": "2794"
    },
    {
      "type": "https://oparl.org/schema/1.0/Consultation",
      "meeting": "2995"
    },
    {
      "type": "https://oparl.org/schema/1.0/Consultation",
      "meeting": "2805"
    },
    {
      "type": "https://oparl.org/schema/1.0/Consultation",
      "meeting": "2753"
    },
    {
      "type": "https://oparl.org/schema/1.0/Consultation",
      "meeting": "3240"
    },
    {
      "type": "https://oparl.org/schema/1.0/Consultation",
      "meeting": "2827"
    },
    {
      "type": "https://oparl.org/schema/1.0/Consultation",
      "meeting": "2783"
    },
    {
      "type": "https://oparl.org/schema/1.0/Consultation",
      "meeting": "2916"
    },
    {
      "type": "https://oparl.org/schema/1.0/Consultation",
      "meeting": "2984"
    },
    {
      "type": "https://oparl.org/schema/1.0/Consultation",
      "meeting": "2816"
    },
    {
      "type": "https://oparl.org/schema/1.0/Consultation",
      "meeting": "3017"
    },
    {
      "type": "https://oparl.org/schema/1.0/Consultation",
      "meeting": "3006"
    },
    {
      "type": "https://oparl.org/schema/1.0/Consultation",
      "meeting": "2856"
    },
    {
      "type": "https://oparl.org/schema/1.0/Consultation",
      "meeting": "2868"
    },
    {
      "type": "https://oparl.org/schema/1.0/Consultation",
      "meeting": "2838"
    },
    {
      "type": "https://oparl.org/schema/1.0/Consultation",
      "meeting": "2594"
    },
    {
      "type": "https://oparl.org/schema/1.0/Consultation",
      "meeting": "2605"
    },
    {
      "type": "https://oparl.org/schema/1.0/Consultation",
      "meeting": "2608"
    },
    {
      "type": "https://oparl.org/schema/1.0/Consultation",
      "meeting": "2622"
    },
    {
      "type": "https://oparl.org/schema/1.0/Consultation",
      "meeting": "2642"
    },
    {
      "type": "https://oparl.org/schema/1.0/Consultation",
      "meeting": "3364"
    }
  ],
  "id": "7332"
}