{
  "name": "Gestaltung Postplatz - Weiteres Vorgehen\n\nhier:\nBaumpflanzungen",
  "shortName": "V0056/14",
  "reference": "V0056/14",
  "publishedDate": "2014-08-27",
  "paperType": "Infovorlage",
  "type": "https://oparl.org/schema/1.0/Paper",
  "mainFile": "188249",
  "auxiliaryFile": [
    "187557",
    "178861",
    "178862",
    "178866"
  ],
  "consultation": [
    {
      "type": "https://oparl.org/schema/1.0/Consultation",
      "meeting": "3509"
    },
    {
      "type": "https://oparl.org/schema/1.0/Consultation",
      "meeting": "3996"
    }
  ],
  "id": "8902"
}