{
  "shortName": "OSR CB/020/2011",
  "locality": "Landeshauptstadt Dresden,  im Bürgersaal der Verwaltungsstelle Cossebaude,Dresdner Straße 3, 01156 Dresden",
  "name": "20. Sitzung des Ortschaftsrates Cossebaude",
  "type": "https://oparl.org/schema/1.0/Meeting",
  "organization": [
    "46"
  ],
  "start": "2011-06-06T18:30:00+02:00",
  "end": "2011-06-06T21:30:00+02:00",
  "invitation": "64722",
  "verbatimProtocol": "66642",
  "agendaItem": [
    {
      "name": "Begrüßung und Feststellung der Beschlussfähigkeit",
      "number": "1",
      "type": "https://oparl.org/schema/1.0/AgendaItem"
    },
    {
      "name": "Bestätigung der Tagesordnung sowie der Niederschrift der Sitzung am 9.Mai 2011",
      "number": "2",
      "type": "https://oparl.org/schema/1.0/AgendaItem"
    },
    {
      "name": "Einwohnerfragestunde",
      "number": "3",
      "type": "https://oparl.org/schema/1.0/AgendaItem"
    },
    {
      "name": "Vorstellung des Feuerwehr- und Heimatvereins Niederwartha",
      "number": "4",
      "type": "https://oparl.org/schema/1.0/AgendaItem"
    },
    {
      "name": "Vorstellung weiterer Planungen und Maßnahmen im Bereich Abwasserkanal und Trinkwasser",
      "number": "5",
      "type": "https://oparl.org/schema/1.0/AgendaItem"
    },
    {
      "name": "Bericht zum Busnetz 2010 und Linienänderungen 2011",
      "number": "6",
      "type": "https://oparl.org/schema/1.0/AgendaItem",
      "consultation": {
        "parentID": "3661",
        "type": "https://oparl.org/schema/1.0/Consultation"
      },
      "resolutionFile": "69580",
      "auxiliaryFile": [
        "62080",
        "118064",
        "60861",
        "55909"
      ]
    },
    {
      "name": "Finanzmittel",
      "number": "7",
      "type": "https://oparl.org/schema/1.0/AgendaItem"
    },
    {
      "name": "Finanzzuschuss zur Deckensanierung Weinbergstraße",
      "number": "7.1",
      "type": "https://oparl.org/schema/1.0/AgendaItem"
    },
    {
      "name": "Finanzmittel für kulturelle Veranstaltungen 2011 für ASB Begegnungsstätte \"Am Friedenssteien\" Cossebaude",
      "number": "7.2",
      "type": "https://oparl.org/schema/1.0/AgendaItem"
    },
    {
      "name": "Finanzmittel für Stele \"Weinsberger Platz\"",
      "number": "7.3",
      "type": "https://oparl.org/schema/1.0/AgendaItem"
    },
    {
      "name": "Informationen und Anfragen",
      "number": "8",
      "type": "https://oparl.org/schema/1.0/AgendaItem"
    }
  ],
  "participant": [
    "306",
    "309",
    "312",
    "308",
    "310",
    "307",
    "313",
    "394"
  ],
  "id": "1298"
}