{
  "id": "http://oparl.dresden.de/bodies/0001/meetings/14859",
  "type": "https://schema.oparl.org/1.1/Meeting",
  "name": "16. Sitzung des Stadtbezirksbeirates Prohlis",
  "start": "2025-11-24T17:00:00+01:00",
  "end": "2025-11-24T19:25:00+01:00",
  "location": {
    "id": "http://oparl.dresden.de/bodies/0001/locations/rm/3255",
    "type": "https://schema.oparl.org/1.1/Location",
    "streetAddress": "",
    "room": "Stadtbezirksamt Prohlis, Bürgersaal",
    "postalCode": "",
    "subLocality": "",
    "locality": "",
    "created": "2018-09-06T11:00:59+02:00",
    "modified": "2018-09-06T11:00:59+02:00"
  },
  "organization": [
    "http://oparl.dresden.de/bodies/0001/organizations/gr/174"
  ],
  "participant": [
    "http://oparl.dresden.de/bodies/0001/people/895",
    "http://oparl.dresden.de/bodies/0001/people/1971",
    "http://oparl.dresden.de/bodies/0001/people/2649",
    "http://oparl.dresden.de/bodies/0001/people/2648",
    "http://oparl.dresden.de/bodies/0001/people/533",
    "http://oparl.dresden.de/bodies/0001/people/1152",
    "http://oparl.dresden.de/bodies/0001/people/1397",
    "http://oparl.dresden.de/bodies/0001/people/1114",
    "http://oparl.dresden.de/bodies/0001/people/2693",
    "http://oparl.dresden.de/bodies/0001/people/2514",
    "http://oparl.dresden.de/bodies/0001/people/2675",
    "http://oparl.dresden.de/bodies/0001/people/542",
    "http://oparl.dresden.de/bodies/0001/people/282",
    "http://oparl.dresden.de/bodies/0001/people/51",
    "http://oparl.dresden.de/bodies/0001/people/73",
    "http://oparl.dresden.de/bodies/0001/people/1513"
  ],
  "invitation": {
    "id": "http://oparl.dresden.de/bodies/0001/files/854916",
    "type": "https://schema.oparl.org/1.1/File",
    "name": "Einladung_SBR Pro",
    "fileName": "00854916.pdf",
    "mimeType": "application/pdf",
    "date": "2025-11-13",
    "accessUrl": "http://oparl.dresden.de/bodies/0001/downloadfiles/a/00854916.pdf",
    "downloadUrl": "http://oparl.dresden.de/bodies/0001/downloadfiles/00854916.pdf",
    "created": "2025-11-13T08:44:54+01:00",
    "modified": "2025-11-14T09:04:46+01:00"
  },
  "agendaItem": [
    {
      "id": "http://oparl.dresden.de/bodies/0001/agendaitems/229754",
      "type": "https://schema.oparl.org/1.1/AgendaItem",
      "meeting": "http://oparl.dresden.de/bodies/0001/meetings/14859",
      "number": "1",
      "order": 1,
      "name": "Eröffnung der Sitzung, Feststellung der Beschlussfähigkeit, Bestätigung der Tagesordnung",
      "public": true,
      "created": "2025-10-27T16:45:59+01:00",
      "modified": "2025-10-27T16:46:01+01:00"
    },
    {
      "id": "http://oparl.dresden.de/bodies/0001/agendaitems/229755",
      "type": "https://schema.oparl.org/1.1/AgendaItem",
      "meeting": "http://oparl.dresden.de/bodies/0001/meetings/14859",
      "number": "1.1",
      "order": 2,
      "name": "Bestätigung der Niederschrift zur 15. Sitzung des Stadtbezirksbeirates am 27.10.2025",
      "public": true,
      "created": "2025-10-27T16:45:59+01:00",
      "modified": "2025-11-03T11:54:06+01:00"
    },
    {
      "id": "http://oparl.dresden.de/bodies/0001/agendaitems/230892",
      "type": "https://schema.oparl.org/1.1/AgendaItem",
      "meeting": "http://oparl.dresden.de/bodies/0001/meetings/14859",
      "number": "2",
      "order": 3,
      "name": "\"Sozialer Zusammenhalt\" Prohlis - Vorstellung des Jahresberichtes 2024 und Zwischenbericht des Jahres 2025 der Quartiersmanage-ments Am Koitzschgraben und Prohlis",
      "public": true,
      "auxiliaryFile": [
        {
          "id": "http://oparl.dresden.de/bodies/0001/files/856975",
          "type": "https://schema.oparl.org/1.1/File",
          "name": "TOP 2_Präsentation-QM Am Koitschgraben_Jahresbericht 2024",
          "fileName": "00856975.pdf",
          "mimeType": "application/pdf",
          "date": "2025-11-25",
          "accessUrl": "http://oparl.dresden.de/bodies/0001/downloadfiles/a/00856975.pdf",
          "downloadUrl": "http://oparl.dresden.de/bodies/0001/downloadfiles/00856975.pdf",
          "created": "2025-11-25T13:08:41+01:00",
          "modified": "2025-11-25T13:08:41+01:00"
        },
        {
          "id": "http://oparl.dresden.de/bodies/0001/files/856976",
          "type": "https://schema.oparl.org/1.1/File",
          "name": "TOP 2_Präsentation-QM Prohlis_Jahresbericht 2024",
          "fileName": "00856976.pdf",
          "mimeType": "application/pdf",
          "date": "2025-11-25",
          "accessUrl": "http://oparl.dresden.de/bodies/0001/downloadfiles/a/00856976.pdf",
          "downloadUrl": "http://oparl.dresden.de/bodies/0001/downloadfiles/00856976.pdf",
          "created": "2025-11-25T13:08:41+01:00",
          "modified": "2025-11-25T13:08:42+01:00"
        }
      ],
      "created": "2025-11-13T08:38:13+01:00",
      "modified": "2025-11-25T13:08:43+01:00"
    },
    {
      "id": "http://oparl.dresden.de/bodies/0001/agendaitems/229756",
      "type": "https://schema.oparl.org/1.1/AgendaItem",
      "meeting": "http://oparl.dresden.de/bodies/0001/meetings/14859",
      "number": "3",
      "order": 4,
      "name": "Vorlagen des Stadtbezirksamtes",
      "public": true,
      "created": "2025-10-27T16:45:59+01:00",
      "modified": "2025-11-13T08:38:13+01:00"
    },
    {
      "id": "http://oparl.dresden.de/bodies/0001/agendaitems/229762",
      "type": "https://schema.oparl.org/1.1/AgendaItem",
      "meeting": "http://oparl.dresden.de/bodies/0001/meetings/14859",
      "number": "3.1",
      "order": 5,
      "name": "Projektförderung durch den Stadtbezirksbeirat Prohlis, hier: Weihnachtszauber für Prohliser Kinder und ihre Familien und technische Ausstattung für den Stadtteilladen im Prohliszentrum Prohlis",
      "public": true,
      "consultation": "http://oparl.dresden.de/bodies/0001/consultations/68009",
      "result": "Zustimmung",
      "created": "2025-10-27T16:45:59+01:00",
      "modified": "2025-11-26T11:22:12+01:00"
    },
    {
      "id": "http://oparl.dresden.de/bodies/0001/agendaitems/229763",
      "type": "https://schema.oparl.org/1.1/AgendaItem",
      "meeting": "http://oparl.dresden.de/bodies/0001/meetings/14859",
      "number": "3.2",
      "order": 6,
      "name": "Projektförderung durch den Stadtbezirksbeirat Prohlis, hier: Kleinprojekt - Küchenzeile im KuRSiF",
      "public": true,
      "consultation": "http://oparl.dresden.de/bodies/0001/consultations/68088",
      "result": "Zustimmung",
      "created": "2025-10-27T16:45:59+01:00",
      "modified": "2025-11-26T11:23:03+01:00"
    },
    {
      "id": "http://oparl.dresden.de/bodies/0001/agendaitems/230119",
      "type": "https://schema.oparl.org/1.1/AgendaItem",
      "meeting": "http://oparl.dresden.de/bodies/0001/meetings/14859",
      "number": "3.3",
      "order": 7,
      "name": "Unterstützung von Maßnahmen gem. Aufgabenabgrenzungsrichtlinie durch den Stadtbezirksbeirat Prohlis, hier: Errichtung eines für die Allgemeinheit zugänglichen Kleinspielfeldes auf dem Gelände des BSZ-E, Boxberger Straße 1",
      "public": true,
      "consultation": "http://oparl.dresden.de/bodies/0001/consultations/68170",
      "result": "Zustimmung",
      "created": "2025-11-03T11:52:40+01:00",
      "modified": "2025-11-26T11:23:57+01:00"
    },
    {
      "id": "http://oparl.dresden.de/bodies/0001/agendaitems/230122",
      "type": "https://schema.oparl.org/1.1/AgendaItem",
      "meeting": "http://oparl.dresden.de/bodies/0001/meetings/14859",
      "number": "3.4",
      "order": 8,
      "name": "Unterstützung von Maßnahmen gem. Aufgabenabgrenzungsrichtlinie durch den Stadtbezirksbeirat Prohlis, hier: Anschaffung und Montage von Dialogdisplays",
      "public": true,
      "consultation": "http://oparl.dresden.de/bodies/0001/consultations/68204",
      "result": "Zustimmung",
      "created": "2025-11-03T11:53:30+01:00",
      "modified": "2025-11-26T11:27:21+01:00"
    },
    {
      "id": "http://oparl.dresden.de/bodies/0001/agendaitems/230120",
      "type": "https://schema.oparl.org/1.1/AgendaItem",
      "meeting": "http://oparl.dresden.de/bodies/0001/meetings/14859",
      "number": "3.5",
      "order": 9,
      "name": "Unterstützung von Maßnahmen gem. Aufgabenabgrenzungsrichtlinie durch den Stadtbezirksbeirat Prohlis, hier: Gehwegertüchtigung Uhdestraße",
      "public": true,
      "consultation": "http://oparl.dresden.de/bodies/0001/consultations/68171",
      "result": "Zustimmung",
      "created": "2025-11-03T11:52:56+01:00",
      "modified": "2025-11-26T11:28:12+01:00"
    },
    {
      "id": "http://oparl.dresden.de/bodies/0001/agendaitems/230121",
      "type": "https://schema.oparl.org/1.1/AgendaItem",
      "meeting": "http://oparl.dresden.de/bodies/0001/meetings/14859",
      "number": "3.6",
      "order": 10,
      "name": "Unterstützung von Maßnahmen gem. Aufgabenabgrenzungsrichtlinie durch den Stadtbezirksbeirat Prohlis, hier: Errichtung eines Spielplatzes in Dresden-Lockwitz, Am Wehr",
      "public": true,
      "consultation": "http://oparl.dresden.de/bodies/0001/consultations/68187",
      "result": "Zustimmung",
      "created": "2025-11-03T11:53:17+01:00",
      "modified": "2025-11-26T11:25:37+01:00"
    },
    {
      "id": "http://oparl.dresden.de/bodies/0001/agendaitems/229759",
      "type": "https://schema.oparl.org/1.1/AgendaItem",
      "meeting": "http://oparl.dresden.de/bodies/0001/meetings/14859",
      "number": "4",
      "order": 11,
      "name": "Hinweise und Anfragen der Stadtbezirksbeiräte",
      "public": true,
      "created": "2025-10-27T16:45:59+01:00",
      "modified": "2025-11-13T08:38:13+01:00"
    },
    {
      "id": "http://oparl.dresden.de/bodies/0001/agendaitems/229760",
      "type": "https://schema.oparl.org/1.1/AgendaItem",
      "meeting": "http://oparl.dresden.de/bodies/0001/meetings/14859",
      "number": "5",
      "order": 12,
      "name": "Informationen des Stadtbezirksamtsleiters/Sonstiges",
      "public": true,
      "created": "2025-10-27T16:45:59+01:00",
      "modified": "2025-11-13T08:38:13+01:00"
    }
  ],
  "created": "2024-11-07T13:43:47+01:00",
  "modified": "2025-11-25T13:36:23+01:00"
}