{
  "shortName": "OSR SB/029/2011",
  "locality": "Landeshauptstadt Dresden,  Beratungsraum im Bürgerhaus (ehem. Gemeindeamt)\nSeifersdorfer Straße 6, 01465 Dresden OT Schönborn",
  "name": "29. Sitzung des Ortschaftsrates Schönborn",
  "type": "https://oparl.org/schema/1.0/Meeting",
  "organization": [
    "50"
  ],
  "start": "2011-12-14T18:30:00+01:00",
  "end": "2011-12-14T20:00:00+01:00",
  "invitation": "83026",
  "verbatimProtocol": "85679",
  "agendaItem": [
    {
      "name": "Vorabsprache Gründung Jugendklub",
      "number": "1",
      "type": "https://oparl.org/schema/1.0/AgendaItem"
    },
    {
      "name": "Fortschreibung der Schulnetzplanung, Planteile Grundschulen, Mittelschulen, Gymnasien, berufsbildende Schulen, Schulen des zweiten Bildungsweges und Schulen in nicht kommunaler Trägerschaft",
      "number": "2",
      "type": "https://oparl.org/schema/1.0/AgendaItem"
    },
    {
      "name": "Umsetzung Beschluss Nr. 13/2011 Fußwegbau",
      "number": "3",
      "type": "https://oparl.org/schema/1.0/AgendaItem"
    },
    {
      "name": "Auswertung Schönborner 7. Advent",
      "number": "4",
      "type": "https://oparl.org/schema/1.0/AgendaItem"
    },
    {
      "name": "Mietvertrag Bürgerhaus - Schimmelbefall - Verschiebung des Neubaus einer Sommerküche im Bürgerhaus",
      "number": "5",
      "type": "https://oparl.org/schema/1.0/AgendaItem"
    },
    {
      "name": "Allgemeines",
      "number": "6",
      "type": "https://oparl.org/schema/1.0/AgendaItem"
    }
  ],
  "participant": [
    "357",
    "362",
    "358",
    "361",
    "356",
    "355",
    "360"
  ],
  "id": "1525"
}