{
  "type": "https://oparl.org/schema/1.0/Meeting",
  "id": "1732",
  "shortName": "SB/047/2012",
  "name": "47. Sitzung des Ausschusses für Stadtentwicklung und Bau",
  "organization": [
    "Ausschuss für Stadtentwicklung und Bau"
  ],
  "start": "2012-02-29T14:00:00Z",
  "end": "2012-02-29T20:10:00Z",
  "locality": "Landeshauptstadt Dresden,  im Ortsamt Altstadt, 1. Etage, Raum 100,\nTheaterstraße 11, 01067 Dresden",
  "participant": [
    "29",
    "38",
    "66",
    "87",
    "640",
    "62",
    "274",
    "716",
    "265",
    "254",
    "887",
    "46"
  ],
  "invitation": "88983",
  "verbatimProtocol": "91258",
  "agendaItem": [
    {
      "name": "Vorhabenbezogener Bebauungsplan Nr. 684, Dresden-Altstadt II, Strehlener Straße - Haus der Bahn\n\n\n\nhier:\t1. Aufstellungsbeschluss vorhabenbezogener Bebauungsplan\n\n\t2. Grenzen des räumlichen Geltungsbereiches des vorhabenbezogenen Bebauungs-\n\n\tplanes",
      "consultation": "5130",
      "number": "1",
      "type": "https://oparl.org/schema/1.0/AgendaItem",
      "resolutionFile": "90252",
      "auxiliaryFile": [
        "81273",
        "80873",
        "80420",
        "80421",
        "80440"
      ]
    },
    {
      "name": "Vorhabenbezogener Bebauungsplan Nr. 6006, Dresden-Cotta, Am Frosch\n\nhier:\n\n1. Aufstellungsbeschluss vorhabenbezogener Bebauungsplan\n\n2. Grenzen des räumlichen Geltungsbereichs des vorhabenbezogenen Bebauungsplanes",
      "consultation": "5233",
      "number": "2",
      "type": "https://oparl.org/schema/1.0/AgendaItem",
      "resolutionFile": "97276",
      "auxiliaryFile": [
        "84253",
        "90311",
        "83376",
        "83763",
        "83381"
      ]
    },
    {
      "name": "Neubesetzungsverfahren Gestaltungskommission Kulturhistorisches Zentrum",
      "consultation": "5328",
      "number": "3",
      "type": "https://oparl.org/schema/1.0/AgendaItem",
      "resolutionFile": "92781",
      "auxiliaryFile": [
        "88850",
        "88466",
        "85722",
        "86513"
      ]
    },
    {
      "name": "Bebauungsplan Nr. 122, Dresden-Altstadt II, Bereich des Verkehrszuges Wiener Straße Â Gellertstraße zwischen Mary-Wigman-Straße und Lennéplatz\n\n\n\nhier:\n\nAufhebung des Aufstellungsbeschlusses zum Bebauungsplan",
      "consultation": "5343",
      "number": "4",
      "type": "https://oparl.org/schema/1.0/AgendaItem",
      "resolutionFile": "90259",
      "auxiliaryFile": [
        "86729",
        "86375",
        "86241",
        "86242",
        "86243"
      ]
    },
    {
      "name": "Bebauungsplan Nr. 214, Dresden-Altstadt I Nr. 25, Westliche Seevorstadt/Vitzthumstraße\n\n\n\nhier:\n\nAufhebung des Aufstellungsbeschlusses zum Bebauungsplan",
      "consultation": "5365",
      "number": "5",
      "type": "https://oparl.org/schema/1.0/AgendaItem",
      "resolutionFile": "90263",
      "auxiliaryFile": [
        "87378",
        "87222",
        "86757",
        "86758",
        "86759",
        "86760"
      ]
    },
    {
      "name": "Vorhabenbezogener Bebauungsplan Nr. 6005, Dresden-Räcknitz, Fraunhofer IVI - Testoval\n\n\n\nhier:\n\n1. Billigung des Entwurfs zum vorhabenbezogenen Bebauungsplan\n\n2. Billigung der Begründung zum vorhabenbezogenen Bebauungsplan-Entwurf\n\n3. Öffentliche Auslegung des Entwurfs zum vorhabenbezogenen Bebauungsplan",
      "consultation": "5389",
      "number": "6",
      "type": "https://oparl.org/schema/1.0/AgendaItem",
      "resolutionFile": "90267",
      "auxiliaryFile": [
        "88038",
        "87742",
        "86977",
        "86978",
        "86979",
        "86980",
        "86981",
        "86982",
        "86983",
        "86984",
        "86985",
        "86987"
      ]
    },
    {
      "name": "Prüfauftrag -Tempo 30 im Lockwitzgrund",
      "consultation": "4964",
      "number": "7",
      "type": "https://oparl.org/schema/1.0/AgendaItem",
      "auxiliaryFile": [
        "76487"
      ]
    },
    {
      "name": "Errichtung einer Fuß- und Fahrradbrücke in Dresden",
      "consultation": "5171",
      "number": "8",
      "type": "https://oparl.org/schema/1.0/AgendaItem",
      "auxiliaryFile": [
        "82320",
        "149757",
        "159315",
        "118016",
        "130277"
      ],
      "resolutionFile": "90278"
    },
    {
      "name": "Informationen/Sonstiges",
      "consultation": null,
      "number": "9",
      "type": "https://oparl.org/schema/1.0/AgendaItem"
    },
    {
      "name": "Maßnahmen- und Finanzierungskonzept zum Elberadweg",
      "consultation": "5411",
      "number": "9.1",
      "type": "https://oparl.org/schema/1.0/AgendaItem",
      "auxiliaryFile": [
        "88039",
        "87746",
        "88871",
        "87509",
        "87510",
        "87511"
      ]
    },
    {
      "name": "Planänderungen zur Neugestaltung des Vorplatzes am Haltepunkt Weixdorf Bad einschließlich P+R",
      "consultation": null,
      "number": "9.2",
      "type": "https://oparl.org/schema/1.0/AgendaItem"
    }
  ]
}