{
  "shortName": "OSR GP/054/2014",
  "locality": "Landeshauptstadt Dresden,  im Gemeindezentrum Gompitz, Gemeindesaal,Altnossener Straße 46 a, 01156 Dresden, OT Pennrich",
  "name": "54. Sitzung des Ortschaftsrates Gompitz",
  "type": "https://oparl.org/schema/1.0/Meeting",
  "organization": [
    "9"
  ],
  "start": "2014-01-06T19:30:00+01:00",
  "end": "2014-01-06T20:25:00+01:00",
  "invitation": "155629",
  "resultsProtocol": "156339",
  "auxiliaryFile": [
    "156393"
  ],
  "agendaItem": [
    {
      "name": "Feststellung ordnungsgemäße Ladung/ Beschlussfähigkeit",
      "number": "1",
      "type": "https://oparl.org/schema/1.0/AgendaItem"
    },
    {
      "name": "Anfragen der Bürger",
      "number": "2",
      "type": "https://oparl.org/schema/1.0/AgendaItem"
    },
    {
      "name": "Beschluss zum Antrag des Obergorbitzer Friedhofes im Kirchspiel Dresden-West auf Gewährung einer Zuwendung für das Projekt Brunnenbohrung",
      "number": "3",
      "type": "https://oparl.org/schema/1.0/AgendaItem",
      "result": "Zustimmung mit Ergänzung",
      "vote": {
        "yes": 12,
        "no": 0,
        "neutral": 0,
        "biased": 0,
        "type": "https://oparl.org/schema/1.0/VoteResult"
      }
    },
    {
      "name": "Beschluss zur Bereitstellung von Verfügungsmitteln des Ortschaftsrates für Vorhaben im Jahr 2014",
      "number": "4",
      "type": "https://oparl.org/schema/1.0/AgendaItem",
      "result": "Zustimmung",
      "vote": {
        "yes": 12,
        "no": 0,
        "neutral": 0,
        "biased": 0,
        "type": "https://oparl.org/schema/1.0/VoteResult"
      }
    },
    {
      "name": "Auswertung und Aktualisierung der Aufgabenstellungen für die Arbeitsgruppen des Ortschaftsrates im Jahr 2014",
      "number": "5",
      "type": "https://oparl.org/schema/1.0/AgendaItem"
    },
    {
      "name": "Bearbeitungsstand Sanierung der Wanderwege im Zschonergrund",
      "number": "6",
      "type": "https://oparl.org/schema/1.0/AgendaItem"
    },
    {
      "name": "Sonstiges",
      "number": "7",
      "type": "https://oparl.org/schema/1.0/AgendaItem"
    }
  ],
  "participant": [
    "322",
    "323",
    "325",
    "319",
    "1133",
    "330",
    "328"
  ],
  "id": "3709"
}