{
  "type": "https://oparl.org/schema/1.0/Meeting",
  "id": "4392",
  "shortName": "AV/IT/017/2015",
  "name": "17. Sitzung des Ausschusses für Allgemeine Verwaltung, Ordnung und Sicherheit\n(Eigenbetrieb IT-Dienstleistungen)",
  "organization": [
    "Ausschuss für Allgemeine Verwaltung, Ordnung und Sicherheit (Eigenbetrieb IT-Dienstleistungen)"
  ],
  "start": "2015-09-07T14:30:00Z",
  "end": "2015-09-07T16:25:00Z",
  "locality": "Landeshauptstadt Dresden,  im Neuen Rathaus, Beratungsraum 3, 3. Etage, Raum 13,\nDr.-Külz-Ring 19, 01067 Dresden",
  "participant": [
    "30",
    "25",
    "38",
    "298",
    "765",
    "61",
    "66",
    "1231",
    "1240",
    "648",
    "79",
    "1234",
    "1235",
    "722",
    "1239",
    "44",
    "46"
  ],
  "invitation": "219233",
  "auxiliaryFile": [
    "220882",
    "220891",
    "220889"
  ],
  "verbatimProtocol": "220986",
  "agendaItem": [
    {
      "name": "Regelungen zur Ausgestaltung der Ausbildungsverträge zwischen der Landeshauptstadt Dresden und den Studentinnen und Studenten der Fachhochschule der Sächsischen Verwaltung Meißen (FHSV Meißen) und der Berufsakademien",
      "consultation": "9442",
      "number": "1",
      "type": "https://oparl.org/schema/1.0/AgendaItem",
      "resolutionFile": "221261",
      "auxiliaryFile": [
        "236535",
        "217081",
        "217058"
      ]
    },
    {
      "name": "Kaufvertrag über das Grundstück Gänsefuß 55 mit einem Stadtrat",
      "consultation": "9781",
      "number": "2",
      "type": "https://oparl.org/schema/1.0/AgendaItem",
      "resolutionFile": "221277",
      "auxiliaryFile": [
        "233817",
        "215760",
        "215337",
        "215272",
        "204093"
      ]
    }
  ],
  "downloaded_at": "2016-03-03T00:59:14Z"
}