{
  "shortName": "OSR LB/031/2017",
  "locality": "Landeshauptstadt Dresden, im kleinen Saal des Bürgerhauses, Hauptstr. 4 (Eingang von Badstr.), 01465 Langebrück",
  "name": "Ortschaftsrat Langebrück - 14.02.2017 - 17:38-21:50 Uhr",
  "type": "https://oparl.org/schema/1.0/Meeting",
  "organization": [
    "51"
  ],
  "start": "2017-02-14T17:38:00+01:00",
  "end": "2017-02-14T21:50:00+01:00",
  "resultsProtocol": "288917",
  "auxiliaryFile": [
    "288918",
    "288431",
    "288430"
  ],
  "invitation": "287454",
  "verbatimProtocol": "290755",
  "agendaItem": [
    {
      "name": "Eröffnung und Begrüßung durch den Ortsvorsteher",
      "number": "Ö 1",
      "type": "https://oparl.org/schema/1.0/AgendaItem"
    },
    {
      "name": "Bekanntgabe von Beschlüssen aus nichtöffentlicher Sitzung des Ortschaftsrates",
      "number": "Ö 2",
      "type": "https://oparl.org/schema/1.0/AgendaItem"
    },
    {
      "name": "Beschlusskontrollen",
      "number": "Ö 3",
      "type": "https://oparl.org/schema/1.0/AgendaItem"
    },
    {
      "name": "Informationen durch den Ortsvorsteher",
      "number": "Ö 4",
      "type": "https://oparl.org/schema/1.0/AgendaItem"
    },
    {
      "name": "Beschluss zu einem Bürgerentscheid nach § 24 SächsGemO",
      "number": "Ö 5",
      "type": "https://oparl.org/schema/1.0/AgendaItem",
      "result": "Zustimmung"
    },
    {
      "name": "Lösungsansätze zur Sicherstellung der Beschulung aller Langebrücker Kinder im Grundschulbezirk in den Jahren 2017/18 und 2018/19",
      "number": "Ö 6",
      "type": "https://oparl.org/schema/1.0/AgendaItem",
      "result": "zur Kenntnis genommen",
      "vote": {
        "yes": 7,
        "no": 0,
        "neutral": 0,
        "biased": 0,
        "type": "https://oparl.org/schema/1.0/VoteResult"
      }
    },
    {
      "name": "Veranstaltungsplanung und Vereinsförderung 2017/Vorstellung Projekte durch Vereine",
      "number": "Ö 7",
      "type": "https://oparl.org/schema/1.0/AgendaItem"
    },
    {
      "name": "Fragen an den Ortschaftsrat",
      "number": "Ö 8",
      "type": "https://oparl.org/schema/1.0/AgendaItem"
    },
    {
      "name": "Termine",
      "number": "Ö 9",
      "type": "https://oparl.org/schema/1.0/AgendaItem"
    },
    {
      "name": "Sonstiges",
      "number": "Ö 10",
      "type": "https://oparl.org/schema/1.0/AgendaItem"
    }
  ],
  "id": "6059",
  "participant": [
    "331",
    "332",
    "1252",
    "1251",
    "338",
    "1253",
    "340",
    "1254"
  ]
}