{
  "id": "http://oparl.dresden.de/bodies/0001/meetings/7599",
  "type": "https://schema.oparl.org/1.1/Meeting",
  "name": "50. Sitzung des Stadtbezirksbeirates Neustadt",
  "start": "2018-12-10T17:30:00+01:00",
  "end": "2018-12-10T21:23:00+01:00",
  "location": {
    "id": "http://oparl.dresden.de/bodies/0001/locations/rm/3252",
    "type": "https://schema.oparl.org/1.1/Location",
    "streetAddress": "",
    "room": "Stadtbezirksamt Neustadt, Bürgersaal",
    "postalCode": "",
    "subLocality": "",
    "locality": "",
    "created": "2018-09-06T10:57:52+02:00",
    "modified": "2018-09-06T10:58:57+02:00"
  },
  "organization": [
    "http://oparl.dresden.de/bodies/0001/organizations/gr/166"
  ],
  "participant": [
    "http://oparl.dresden.de/bodies/0001/people/893",
    "http://oparl.dresden.de/bodies/0001/people/641",
    "http://oparl.dresden.de/bodies/0001/people/642",
    "http://oparl.dresden.de/bodies/0001/people/1111",
    "http://oparl.dresden.de/bodies/0001/people/1370",
    "http://oparl.dresden.de/bodies/0001/people/1196",
    "http://oparl.dresden.de/bodies/0001/people/1372",
    "http://oparl.dresden.de/bodies/0001/people/1365",
    "http://oparl.dresden.de/bodies/0001/people/650",
    "http://oparl.dresden.de/bodies/0001/people/653",
    "http://oparl.dresden.de/bodies/0001/people/1369",
    "http://oparl.dresden.de/bodies/0001/people/1515",
    "http://oparl.dresden.de/bodies/0001/people/655",
    "http://oparl.dresden.de/bodies/0001/people/660",
    "http://oparl.dresden.de/bodies/0001/people/662",
    "http://oparl.dresden.de/bodies/0001/people/1361",
    "http://oparl.dresden.de/bodies/0001/people/664",
    "http://oparl.dresden.de/bodies/0001/people/1359"
  ],
  "invitation": {
    "id": "http://oparl.dresden.de/bodies/0001/files/382302",
    "type": "https://schema.oparl.org/1.1/File",
    "name": "Einladung_SBR Neu_2018_12_10",
    "fileName": "00382302.pdf",
    "mimeType": "application/pdf",
    "date": "2018-11-28",
    "accessUrl": "http://oparl.dresden.de/bodies/0001/downloadfiles/a/00382302.pdf",
    "downloadUrl": "http://oparl.dresden.de/bodies/0001/downloadfiles/00382302.pdf",
    "created": "2018-11-28T11:06:19+01:00",
    "modified": "2018-11-30T09:05:53+01:00"
  },
  "auxiliaryFile": [
    {
      "id": "http://oparl.dresden.de/bodies/0001/files/384942",
      "type": "https://schema.oparl.org/1.1/File",
      "name": "Beschlussempfehlung_Stadtbezirksbeirat Neustadt_A0436/18_mU",
      "fileName": "00384942.pdf",
      "mimeType": "application/pdf",
      "date": "2018-12-11",
      "accessUrl": "http://oparl.dresden.de/bodies/0001/downloadfiles/a/00384942.pdf",
      "downloadUrl": "http://oparl.dresden.de/bodies/0001/downloadfiles/00384942.pdf",
      "created": "2018-12-11T12:27:25+01:00",
      "modified": "2019-03-07T10:59:52+01:00"
    },
    {
      "id": "http://oparl.dresden.de/bodies/0001/files/384943",
      "type": "https://schema.oparl.org/1.1/File",
      "name": "Beschlussempfehlung_Stadtbezirksbeirat Neustadt_A0487/18_mU",
      "fileName": "00384943.pdf",
      "mimeType": "application/pdf",
      "date": "2018-12-11",
      "accessUrl": "http://oparl.dresden.de/bodies/0001/downloadfiles/a/00384943.pdf",
      "downloadUrl": "http://oparl.dresden.de/bodies/0001/downloadfiles/00384943.pdf",
      "created": "2018-12-11T12:27:27+01:00",
      "modified": "2019-03-07T10:59:52+01:00"
    },
    {
      "id": "http://oparl.dresden.de/bodies/0001/files/384944",
      "type": "https://schema.oparl.org/1.1/File",
      "name": "Beschlussempfehlung_Stadtbezirksbeirat Neustadt_V2665/18_mU",
      "fileName": "00384944.pdf",
      "mimeType": "application/pdf",
      "date": "2018-12-11",
      "accessUrl": "http://oparl.dresden.de/bodies/0001/downloadfiles/a/00384944.pdf",
      "downloadUrl": "http://oparl.dresden.de/bodies/0001/downloadfiles/00384944.pdf",
      "created": "2018-12-11T12:27:28+01:00",
      "modified": "2019-03-07T10:59:52+01:00"
    },
    {
      "id": "http://oparl.dresden.de/bodies/0001/files/384945",
      "type": "https://schema.oparl.org/1.1/File",
      "name": "Beschlussempfehlung_Stadtbezirksbeirat Neustadt_V2702/18_mU",
      "fileName": "00384945.pdf",
      "mimeType": "application/pdf",
      "date": "2018-12-11",
      "accessUrl": "http://oparl.dresden.de/bodies/0001/downloadfiles/a/00384945.pdf",
      "downloadUrl": "http://oparl.dresden.de/bodies/0001/downloadfiles/00384945.pdf",
      "created": "2018-12-11T12:27:29+01:00",
      "modified": "2019-03-07T10:59:52+01:00"
    },
    {
      "id": "http://oparl.dresden.de/bodies/0001/files/385319",
      "type": "https://schema.oparl.org/1.1/File",
      "name": "Beschlussempfehlung_Stadtbezirksbeirat Neustadt_V2732_18_mU",
      "fileName": "00385319.pdf",
      "mimeType": "application/pdf",
      "date": "2018-12-12",
      "accessUrl": "http://oparl.dresden.de/bodies/0001/downloadfiles/a/00385319.pdf",
      "downloadUrl": "http://oparl.dresden.de/bodies/0001/downloadfiles/00385319.pdf",
      "created": "2018-12-12T14:31:39+01:00",
      "modified": "2019-03-07T10:59:52+01:00"
    },
    {
      "id": "http://oparl.dresden.de/bodies/0001/files/388740",
      "type": "https://schema.oparl.org/1.1/File",
      "name": "Niederschrift öffentlich",
      "fileName": "00388740.pdf",
      "mimeType": "application/pdf",
      "date": "2019-01-10",
      "accessUrl": "http://oparl.dresden.de/bodies/0001/downloadfiles/a/00388740.pdf",
      "downloadUrl": "http://oparl.dresden.de/bodies/0001/downloadfiles/00388740.pdf",
      "created": "2019-01-10T12:16:00+01:00",
      "modified": "2019-03-07T10:59:52+01:00"
    }
  ],
  "agendaItem": [
    {
      "id": "http://oparl.dresden.de/bodies/0001/agendaitems/109037",
      "type": "https://schema.oparl.org/1.1/AgendaItem",
      "meeting": "http://oparl.dresden.de/bodies/0001/meetings/7599",
      "number": "1",
      "order": 1,
      "name": "Kontrolle der Niederschrift zur 49. Sitzung des Stadtbezirksbeirates am 12.11.2018",
      "public": true,
      "created": "2018-11-06T10:00:35+01:00",
      "modified": "2022-12-20T14:43:16+01:00"
    },
    {
      "id": "http://oparl.dresden.de/bodies/0001/agendaitems/111021",
      "type": "https://schema.oparl.org/1.1/AgendaItem",
      "meeting": "http://oparl.dresden.de/bodies/0001/meetings/7599",
      "number": "2",
      "order": 2,
      "name": "Vorstellung des BRN-Gutachtens durch das Stadtteilhaus Dresden-Äußere Neustadt e. V.",
      "public": true,
      "created": "2018-11-27T14:19:19+01:00",
      "modified": "2022-12-20T14:43:16+01:00"
    },
    {
      "id": "http://oparl.dresden.de/bodies/0001/agendaitems/109039",
      "type": "https://schema.oparl.org/1.1/AgendaItem",
      "meeting": "http://oparl.dresden.de/bodies/0001/meetings/7599",
      "number": "3",
      "order": 3,
      "name": "Anträge und Vorlagen zur Beratung und Berichterstattung an die Gremien des Stadtrates",
      "public": true,
      "created": "2018-11-06T10:00:35+01:00",
      "modified": "2022-12-20T14:43:16+01:00"
    },
    {
      "id": "http://oparl.dresden.de/bodies/0001/agendaitems/110659",
      "type": "https://schema.oparl.org/1.1/AgendaItem",
      "meeting": "http://oparl.dresden.de/bodies/0001/meetings/7599",
      "number": "3.1",
      "order": 4,
      "name": "Verkauf des Grundstückes An der Dreikönigskirche 1",
      "public": true,
      "consultation": "http://oparl.dresden.de/bodies/0001/consultations/34481",
      "result": "Ablehnung",
      "created": "2018-11-19T09:18:19+01:00",
      "modified": "2022-12-20T14:43:16+01:00"
    },
    {
      "id": "http://oparl.dresden.de/bodies/0001/agendaitems/110938",
      "type": "https://schema.oparl.org/1.1/AgendaItem",
      "meeting": "http://oparl.dresden.de/bodies/0001/meetings/7599",
      "number": "3.2",
      "order": 5,
      "name": "151. Oberschule, Königsbrücker Str. 115 in 01099 Dresden - Neubau Schulgebäude mit Zweifeldschulsporthalle, einschließlich Sport- und Pausenfreiflächen",
      "public": true,
      "consultation": "http://oparl.dresden.de/bodies/0001/consultations/34754",
      "result": "Zustimmung",
      "created": "2018-11-26T09:17:00+01:00",
      "modified": "2022-12-20T14:43:16+01:00"
    },
    {
      "id": "http://oparl.dresden.de/bodies/0001/agendaitems/111029",
      "type": "https://schema.oparl.org/1.1/AgendaItem",
      "meeting": "http://oparl.dresden.de/bodies/0001/meetings/7599",
      "number": "3.3",
      "order": 6,
      "name": "Ausschreibung von Dienstleistungskonzessionen zur Bewirtschaftung der Dresdner Wochenmärkte  für den Konzessionszeitraum  1. Februar 2020 bis 31. Januar 2023 mit einer einseitigen Verlängerungsoption bis 31. Januar 2025 durch die Konzessionsgeberin/Ä",
      "public": true,
      "consultation": "http://oparl.dresden.de/bodies/0001/consultations/34937",
      "result": "Zustimmung mit Ergänzung",
      "created": "2018-11-28T09:15:02+01:00",
      "modified": "2022-12-20T14:43:16+01:00"
    },
    {
      "id": "http://oparl.dresden.de/bodies/0001/agendaitems/109395",
      "type": "https://schema.oparl.org/1.1/AgendaItem",
      "meeting": "http://oparl.dresden.de/bodies/0001/meetings/7599",
      "number": "3.4",
      "order": 7,
      "name": "Stadtteilangepasste Mobilitätsplanung für die Louisenstraße",
      "public": true,
      "consultation": "http://oparl.dresden.de/bodies/0001/consultations/34383",
      "result": "Zustimmung mit Ergänzung",
      "created": "2018-11-12T14:59:06+01:00",
      "modified": "2022-12-20T14:43:16+01:00"
    },
    {
      "id": "http://oparl.dresden.de/bodies/0001/agendaitems/109394",
      "type": "https://schema.oparl.org/1.1/AgendaItem",
      "meeting": "http://oparl.dresden.de/bodies/0001/meetings/7599",
      "number": "3.5",
      "order": 8,
      "name": "Bürgerbeteiligungssatzung",
      "public": true,
      "consultation": "http://oparl.dresden.de/bodies/0001/consultations/35209",
      "result": "Zustimmung",
      "created": "2018-11-12T14:58:49+01:00",
      "modified": "2022-12-20T14:43:16+01:00"
    },
    {
      "id": "http://oparl.dresden.de/bodies/0001/agendaitems/109040",
      "type": "https://schema.oparl.org/1.1/AgendaItem",
      "meeting": "http://oparl.dresden.de/bodies/0001/meetings/7599",
      "number": "4",
      "order": 9,
      "name": "Informationen, Hinweise und Anfragen",
      "public": true,
      "created": "2018-11-06T10:00:35+01:00",
      "modified": "2022-12-20T14:43:16+01:00"
    }
  ],
  "created": "2018-09-10T16:57:07+02:00",
  "modified": "2020-12-04T09:34:10+01:00"
}