{
  "id": "http://oparl.dresden.de/bodies/0001/agendaitems/186144",
  "type": "https://schema.oparl.org/1.1/AgendaItem",
  "meeting": "http://oparl.dresden.de/bodies/0001/meetings/12722",
  "number": "4",
  "order": 4,
  "name": "Vereinsförderung- Antrag des Ev.- Luth. Kirchspiel Dresdner Heidebogen zur Sanierung der Weixdorfer Kirche- 2.BA",
  "public": true,
  "consultation": "http://oparl.dresden.de/bodies/0001/consultations/57335",
  "created": "2023-06-05T12:05:13+02:00",
  "modified": "2023-06-08T18:40:14+02:00"
}