{
  "id": "http://oparl.dresden.de/bodies/0001/agendaitems/203148",
  "type": "https://schema.oparl.org/1.1/AgendaItem",
  "meeting": "http://oparl.dresden.de/bodies/0001/meetings/13705",
  "number": "37",
  "order": 72,
  "name": "Interkulturelles Engagement würdigen – Dresdner Integrationspreis wiederbeleben",
  "public": true,
  "consultation": "http://oparl.dresden.de/bodies/0001/consultations/61092",
  "result": "Vertagung nach 21 Uhr",
  "created": "2024-05-13T13:45:20+02:00",
  "modified": "2024-06-14T20:29:28+02:00"
}