{
  "id": "http://oparl.dresden.de/bodies/0001/agendaitems/214144",
  "type": "https://schema.oparl.org/1.1/AgendaItem",
  "meeting": "http://oparl.dresden.de/bodies/0001/meetings/15002",
  "number": "3",
  "order": 3,
  "name": "Ausscheiden einer am 9. Juni 2024 in den Ortschaftsrat Oberwartha gewählten Person und Nachrücken einer Ersatzperson",
  "public": true,
  "consultation": "http://oparl.dresden.de/bodies/0001/consultations/64919",
  "result": "Zustimmung",
  "created": "2025-01-07T13:45:34+01:00",
  "modified": "2025-01-29T08:20:48+01:00"
}