{
  "id": "http://oparl.dresden.de/bodies/0001/files/142586",
  "type": "https://schema.oparl.org/1.1/File",
  "name": "Einladung_BW",
  "fileName": "00142586.pdf",
  "mimeType": "application/pdf",
  "date": "2013-09-04",
  "accessUrl": "http://oparl.dresden.de/bodies/0001/downloadfiles/a/00142586.pdf",
  "downloadUrl": "http://oparl.dresden.de/bodies/0001/downloadfiles/00142586.pdf",
  "meeting": [
    "http://oparl.dresden.de/bodies/0001/meetings/2585"
  ],
  "created": "2016-12-21T10:06:30+01:00",
  "modified": "2017-10-06T10:38:47+02:00"
}