{
  "id": "http://oparl.dresden.de/bodies/0001/files/439092",
  "type": "https://schema.oparl.org/1.1/File",
  "name": "V0038/19",
  "fileName": "00439092.pdf",
  "mimeType": "application/pdf",
  "date": "2019-10-29",
  "accessUrl": "http://oparl.dresden.de/bodies/0001/downloadfiles/a/00439092.pdf",
  "downloadUrl": "http://oparl.dresden.de/bodies/0001/downloadfiles/00439092.pdf",
  "paper": [
    "http://oparl.dresden.de/bodies/0001/papers/vo/17754"
  ],
  "created": "2019-10-29T13:35:28+01:00",
  "modified": "2019-10-29T13:35:38+01:00"
}