{
  "id": "http://oparl.dresden.de/bodies/0001/files/441997",
  "type": "https://schema.oparl.org/1.1/File",
  "name": "Anlage 1 Praesentation zu TOP 2_1 und 2_2",
  "fileName": "00441997.pdf",
  "mimeType": "application/pdf",
  "date": "2019-11-11",
  "accessUrl": "http://oparl.dresden.de/bodies/0001/downloadfiles/a/00441997.pdf",
  "downloadUrl": "http://oparl.dresden.de/bodies/0001/downloadfiles/00441997.pdf",
  "meeting": [
    "http://oparl.dresden.de/bodies/0001/meetings/8444"
  ],
  "created": "2019-11-11T11:59:34+01:00",
  "modified": "2020-01-10T11:54:11+01:00"
}