{
  "id": "http://oparl.dresden.de/bodies/0001/files/444686",
  "type": "https://schema.oparl.org/1.1/File",
  "name": "V-Pi00007/19",
  "fileName": "00444686.pdf",
  "mimeType": "application/pdf",
  "date": "2019-11-21",
  "accessUrl": "http://oparl.dresden.de/bodies/0001/downloadfiles/a/00444686.pdf",
  "downloadUrl": "http://oparl.dresden.de/bodies/0001/downloadfiles/00444686.pdf",
  "paper": [
    "http://oparl.dresden.de/bodies/0001/papers/vo/18043"
  ],
  "created": "2019-11-21T08:40:05+01:00",
  "modified": "2019-11-21T08:40:29+01:00"
}