{
  "id": "http://oparl.dresden.de/bodies/0001/files/445319",
  "type": "https://schema.oparl.org/1.1/File",
  "name": "Beschlussausfertigung_Ortschaftsrat Langebrück V-LB0146/19_mU",
  "fileName": "00445319.pdf",
  "mimeType": "application/pdf",
  "date": "2019-11-25",
  "accessUrl": "http://oparl.dresden.de/bodies/0001/downloadfiles/a/00445319.pdf",
  "downloadUrl": "http://oparl.dresden.de/bodies/0001/downloadfiles/00445319.pdf",
  "meeting": [
    "http://oparl.dresden.de/bodies/0001/meetings/8555"
  ],
  "created": "2019-11-25T08:11:39+01:00",
  "modified": "2019-12-04T12:46:18+01:00"
}