{
  "id": "http://oparl.dresden.de/bodies/0001/files/451577",
  "type": "https://schema.oparl.org/1.1/File",
  "name": "Beschlussausfertigung_GKH_V3305_19_mU",
  "fileName": "00451577.pdf",
  "mimeType": "application/pdf",
  "date": "2020-01-06",
  "accessUrl": "http://oparl.dresden.de/bodies/0001/downloadfiles/a/00451577.pdf",
  "downloadUrl": "http://oparl.dresden.de/bodies/0001/downloadfiles/00451577.pdf",
  "paper": [
    "http://oparl.dresden.de/bodies/0001/papers/vo/17547"
  ],
  "created": "2020-01-06T15:04:11+01:00",
  "modified": "2020-01-06T15:04:12+01:00"
}