{
  "id": "http://oparl.dresden.de/bodies/0001/files/462625",
  "type": "https://schema.oparl.org/1.1/File",
  "name": "Entwurfsplanung",
  "fileName": "00462625.pdf",
  "mimeType": "application/pdf",
  "date": "2020-03-04",
  "accessUrl": "http://oparl.dresden.de/bodies/0001/downloadfiles/a/00462625.pdf",
  "downloadUrl": "http://oparl.dresden.de/bodies/0001/downloadfiles/00462625.pdf",
  "paper": [
    "http://oparl.dresden.de/bodies/0001/papers/vo/18535"
  ],
  "created": "2020-03-04T13:26:44+01:00",
  "modified": "2020-03-24T15:16:34+01:00"
}