{
  "id": "http://oparl.dresden.de/bodies/0001/files/531085",
  "type": "https://schema.oparl.org/1.1/File",
  "name": "Ausfertigung Vorschlag_SBR Pieschen_VorR-Pi00005/21_oU",
  "fileName": "00531085.pdf",
  "mimeType": "application/pdf",
  "date": "2021-03-10",
  "accessUrl": "http://oparl.dresden.de/bodies/0001/downloadfiles/a/00531085.pdf",
  "downloadUrl": "http://oparl.dresden.de/bodies/0001/downloadfiles/00531085.pdf",
  "paper": [
    "http://oparl.dresden.de/bodies/0001/papers/vo/7662",
    "http://oparl.dresden.de/bodies/0001/papers/ag/7662"
  ],
  "created": "2021-03-10T08:19:16+01:00",
  "modified": "2021-03-10T09:33:00+01:00"
}