{
  "id": "http://oparl.dresden.de/bodies/0001/files/567181",
  "type": "https://schema.oparl.org/1.1/File",
  "name": "Niederschrift_mU",
  "fileName": "00567181.pdf",
  "mimeType": "application/pdf",
  "date": "2021-09-16",
  "accessUrl": "http://oparl.dresden.de/bodies/0001/downloadfiles/a/00567181.pdf",
  "downloadUrl": "http://oparl.dresden.de/bodies/0001/downloadfiles/00567181.pdf",
  "meeting": [
    "http://oparl.dresden.de/bodies/0001/meetings/10024"
  ],
  "created": "2021-09-16T11:22:26+02:00",
  "modified": "2021-09-16T11:22:31+02:00"
}