{
  "id": "http://oparl.dresden.de/bodies/0001/files/594045",
  "type": "https://schema.oparl.org/1.1/File",
  "name": "Anlage 3_Rechenschaftsbericht 2020",
  "fileName": "00594045.pdf",
  "mimeType": "application/pdf",
  "date": "2022-02-17",
  "accessUrl": "http://oparl.dresden.de/bodies/0001/downloadfiles/a/00594045.pdf",
  "downloadUrl": "http://oparl.dresden.de/bodies/0001/downloadfiles/00594045.pdf",
  "paper": [
    "http://oparl.dresden.de/bodies/0001/papers/vo/22871"
  ],
  "created": "2022-02-17T14:50:28+01:00",
  "modified": "2022-03-22T16:04:43+01:00"
}