{
  "id": "http://oparl.dresden.de/bodies/0001/files/646358",
  "type": "https://schema.oparl.org/1.1/File",
  "name": "Anfrage DIE LINKE.",
  "fileName": "00646358.pdf",
  "mimeType": "application/pdf",
  "date": "2022-11-07",
  "accessUrl": "http://oparl.dresden.de/bodies/0001/downloadfiles/a/00646358.pdf",
  "downloadUrl": "http://oparl.dresden.de/bodies/0001/downloadfiles/00646358.pdf",
  "paper": [
    "http://oparl.dresden.de/bodies/0001/papers/vo/9348"
  ],
  "created": "2022-11-07T16:34:22+01:00",
  "modified": "2022-12-30T14:54:58+01:00"
}