{
  "id": "http://oparl.dresden.de/bodies/0001/files/689839",
  "type": "https://schema.oparl.org/1.1/File",
  "name": "Beschlussempfehlung_F_V2269_23_ff",
  "fileName": "00689839.pdf",
  "mimeType": "application/pdf",
  "date": "2023-06-07",
  "accessUrl": "http://oparl.dresden.de/bodies/0001/downloadfiles/a/00689839.pdf",
  "downloadUrl": "http://oparl.dresden.de/bodies/0001/downloadfiles/00689839.pdf",
  "paper": [
    "http://oparl.dresden.de/bodies/0001/papers/vo/25210"
  ],
  "created": "2023-06-07T11:10:46+02:00",
  "modified": "2023-06-07T11:10:47+02:00"
}