{
  "id": "http://oparl.dresden.de/bodies/0001/files/703190",
  "type": "https://schema.oparl.org/1.1/File",
  "name": "Ergänzungsantrag_SB_V2176_23_Grüne_2023_08_23",
  "fileName": "00703190.pdf",
  "mimeType": "application/pdf",
  "date": "2023-08-23",
  "accessUrl": "http://oparl.dresden.de/bodies/0001/downloadfiles/a/00703190.pdf",
  "downloadUrl": "http://oparl.dresden.de/bodies/0001/downloadfiles/00703190.pdf",
  "paper": [
    "http://oparl.dresden.de/bodies/0001/papers/vo/24928"
  ],
  "created": "2023-08-23T18:29:13+02:00",
  "modified": "2023-08-23T18:31:40+02:00"
}