{
  "id": "http://oparl.dresden.de/bodies/0001/files/735766",
  "type": "https://schema.oparl.org/1.1/File",
  "name": "Vorlage Neustadt V-Neu00254_24 mit Unterschrift",
  "fileName": "00735766.pdf",
  "mimeType": "application/pdf",
  "date": "2024-02-08",
  "accessUrl": "http://oparl.dresden.de/bodies/0001/downloadfiles/a/00735766.pdf",
  "downloadUrl": "http://oparl.dresden.de/bodies/0001/downloadfiles/00735766.pdf",
  "paper": [
    "http://oparl.dresden.de/bodies/0001/papers/vo/26363"
  ],
  "created": "2024-02-08T15:10:46+01:00",
  "modified": "2024-02-08T15:13:52+01:00"
}