{
  "id": "http://oparl.dresden.de/bodies/0001/files/754348",
  "type": "https://schema.oparl.org/1.1/File",
  "name": "Antrag",
  "fileName": "00754348.pdf",
  "mimeType": "application/pdf",
  "date": "2024-04-30",
  "accessUrl": "http://oparl.dresden.de/bodies/0001/downloadfiles/a/00754348.pdf",
  "downloadUrl": "http://oparl.dresden.de/bodies/0001/downloadfiles/00754348.pdf",
  "paper": [
    "http://oparl.dresden.de/bodies/0001/papers/vo/26985"
  ],
  "created": "2024-04-30T10:56:02+02:00",
  "modified": "2024-04-30T11:28:53+02:00"
}